setup.py
ban_commons.egg-info/PKG-INFO
ban_commons.egg-info/SOURCES.txt
ban_commons.egg-info/dependency_links.txt
ban_commons.egg-info/top_level.txt
generate/__init__.py
generate/application.py
generate/generate_code_service.py