Metadata-Version: 1.0
Name: ban-commons
Version: 0.0.1
Summary: eking commons
Home-page: http://liluo.org
Author: zhaowenlei
Author-email: zhaowenlei789@sina.com
License: MIT License
Keywords: ban,commons
Platform: any
